matexp/__init__.py
matexp/__main__.py
matexp/approx.py
matexp/codegen.py
matexp/inputs.py
matexp/lti_model.py
matexp/nmodl_compiler.py
matexp/optimizer.py
matexp/polynomial.py
matexp/tests/NMDA.mod
matexp/tests/Nav11.mod
matexp/tests/ampa13.mod
matexp/tests/nonlinear.mod
matexp/tests/test_error.py
matexp/tests/test_inputs.py
matexp/tests/test_main.py
matexp/tests/test_nmodl.py
matexp/tests/test_polynomial.py
matexp-1.0.0.dist-info/LICENSE.txt
matexp-1.0.0.dist-info/METADATA
matexp-1.0.0.dist-info/WHEEL
matexp-1.0.0.dist-info/entry_points.txt
matexp-1.0.0.dist-info/top_level.txt
matexp-1.0.0.dist-info/RECORD
